{
    "currentPage": 1267,
    "pageSize": 5,
    "items": [
        {
            "videoId": "VuwdtOMpBWU",
            "title": "The Woodsmen: Mike and Steve Collect Water (S1, E3) | History",
            "secondDuration": 83,
            "group": "group_12"
        },
        {
            "videoId": "vUJolxzQpfk",
            "title": "Pearl Harbor: The Last Word - Paving the Way: Nelson Mitchell | History",
            "secondDuration": 381,
            "group": "group_12"
        },
        {
            "videoId": "N67WZISiaIE",
            "title": "Alone: Larry Really Doesn't Like Mice (Season 5 Reunion) | History",
            "secondDuration": 88,
            "group": "group_12"
        },
        {
            "videoId": "-VMEXO0FWec",
            "title": "The Curse of Oak Island: Pipe Problems (S3, E2) | History",
            "secondDuration": 116,
            "group": "group_12"
        },
        {
            "videoId": "S1UXwcMdlyk",
            "title": "Swamp People: Tornadoes in Houma | History",
            "secondDuration": 92,
            "group": "group_12"
        }
    ],
    "nbPages": 1444,
    "nbResults": 7217
}