{
    "currentPage": 297,
    "pageSize": 5,
    "items": [
        {
            "videoId": "0mYK2lLowkI",
            "title": "Food Wishes Recipes - \"Special\" Roasted Potatoes Recipe - Crunchy Roasted Potatoes",
            "secondDuration": 135,
            "group": "group_3"
        },
        {
            "videoId": "V1XzgX2eiYY",
            "title": "Borscht-Braised Beef Short Ribs - Beef Short Ribs Braised with Beets",
            "secondDuration": 385,
            "group": "group_3"
        },
        {
            "videoId": "2q4IdyIF__c",
            "title": "Cottage Fries - Easy Oven-Fried Potato Rounds",
            "secondDuration": 239,
            "group": "group_3"
        },
        {
            "videoId": "l7Q0TSnCiFU",
            "title": "Poutine – Beef Gravy Fries & Cheese – Food Wishes",
            "secondDuration": 473,
            "group": "group_3"
        },
        {
            "videoId": "m1UgkRx6mWU",
            "title": "Pork Agrodolce (Italian Sweet & Sour Pork) - Food Wishes",
            "secondDuration": 377,
            "group": "group_3"
        }
    ],
    "nbPages": 360,
    "nbResults": 1799
}