{
    "currentPage": 755,
    "pageSize": 5,
    "items": [
        {
            "videoId": "uzubdMvh93Q",
            "title": "Harry Connick Jr. Finds Jimmy's '70s Doppelgänger",
            "secondDuration": 119,
            "group": "group_10"
        },
        {
            "videoId": "nrmfv7iD8HA",
            "title": "Cara Delevingne Plays \"Sweet Home Alabama\" on Guitar Behind Her Back",
            "secondDuration": 108,
            "group": "group_10"
        },
        {
            "videoId": "hISSsaIvUSU",
            "title": "Paris Jackson Got Starstruck When She Met Fave Alice Cooper",
            "secondDuration": 211,
            "group": "group_10"
        },
        {
            "videoId": "5rGv_SjT47A",
            "title": "Jimmy Fallon's Top 10 List: Why Letterman's Retiring",
            "secondDuration": 228,
            "group": "group_10"
        },
        {
            "videoId": "jqN_DeghUPM",
            "title": "Jim Parsons Says Sheldon Would Thrive During the COVID-19 Pandemic",
            "secondDuration": 490,
            "group": "group_10"
        }
    ],
    "nbPages": 1498,
    "nbResults": 7488
}