{
    "currentPage": 7107,
    "pageSize": 5,
    "items": [
        {
            "videoId": "HUm5ECsj5j0",
            "title": "ABC News Prime: TX hostage situation details; Airline CEO on 5G; Convo. with NHL's 1st Black player",
            "secondDuration": 5337,
            "group": "group_7"
        },
        {
            "videoId": "N_mu7TRI9TU",
            "title": "ABC News Prime: Coronavirus global spread, Grand Princess cruise ship, Market meltdown",
            "secondDuration": 5106,
            "group": "group_7"
        },
        {
            "videoId": "oSRkCAWpMzE",
            "title": "President Trump announces Judge Brett Kavanaugh  as his Supreme Court pick",
            "secondDuration": 7005,
            "group": "group_7"
        },
        {
            "videoId": "wgFNpVMIw3A",
            "title": "Tornado Video 2013: Extraordinary Video From Inside a Tornado Caught on Tape",
            "secondDuration": 147,
            "group": "group_7"
        },
        {
            "videoId": "FluFxJq5ZUM",
            "title": "Arsenio Hall Suing Sinead O'Connor for $5 Million",
            "secondDuration": 41,
            "group": "group_7"
        }
    ],
    "nbPages": 13408,
    "nbResults": 67037
}