{
    "currentPage": 4503,
    "pageSize": 10,
    "items": [
        {
            "videoId": "xC6FbL0VSKo",
            "title": "By the Numbers: War in Ukraine driving up wheat, corn prices",
            "secondDuration": 71,
            "group": "group_7"
        },
        {
            "videoId": "LDuiZ6UaGOU",
            "title": "Kristen Stewart Affair; Jackson Feud",
            "secondDuration": 304,
            "group": "group_7"
        },
        {
            "videoId": "mbEZ_UcxPsc",
            "title": "Sen. Marco Rubio reacts to US military strike in Syria",
            "secondDuration": 227,
            "group": "group_7"
        },
        {
            "videoId": "I6HFDcsW6qw",
            "title": "Ebola Infected Aid Workers to Be Treated in Emory Isolation Room",
            "secondDuration": 148,
            "group": "group_7"
        },
        {
            "videoId": "i0JZcjDiJiI",
            "title": "Florida Teen Arrested After Allegedly Posing as Doctor",
            "secondDuration": 113,
            "group": "group_7"
        },
        {
            "videoId": "FnW7eS6rW1c",
            "title": "Getting Through Flu Season",
            "secondDuration": 180,
            "group": "group_7"
        },
        {
            "videoId": "GVdWACz2g04",
            "title": "Smash, Cash and Grab",
            "secondDuration": 345,
            "group": "group_7"
        },
        {
            "videoId": "Lq5Wq8M401U",
            "title": "The Rundown: Top headlines today: March 31, 2022",
            "secondDuration": 243,
            "group": "group_7"
        },
        {
            "videoId": "zhas-S8NRc4",
            "title": "Warriors Vs Cavs Game 2 Highlights NBA Finals | Curry and Lebron James Battle Again",
            "secondDuration": 113,
            "group": "group_7"
        },
        {
            "videoId": "jqiEdTHgQYI",
            "title": "Rielle Hunter Interview: 'John Edwards and I Are No Longer A Couple'",
            "secondDuration": 306,
            "group": "group_7"
        }
    ],
    "nbPages": 6704,
    "nbResults": 67038
}