{
    "currentPage": 6,
    "pageSize": 50,
    "items": [
        {
            "videoId": "UiGX8b7iem8",
            "title": "Olive Tree - I'm Gone (Lyrics)",
            "secondDuration": 201,
            "group": "group_4"
        },
        {
            "videoId": "W1xaD_RgxHo",
            "title": "Jaymes Young - Infinity (Lyrics) \"cause i love you for infinity\"",
            "secondDuration": 228,
            "group": "group_4"
        },
        {
            "videoId": "oAwKJ0nepxU",
            "title": "Ed Sheeran - Shape of You (Lyrics)",
            "secondDuration": 234,
            "group": "group_4"
        },
        {
            "videoId": "l2qCrrVXGsw",
            "title": "Pink Sweat$ - At My Worst (Remix) [Lyrics] Ft. Kehlani",
            "secondDuration": 170,
            "group": "group_4"
        },
        {
            "videoId": "y_a1uOiBFeY",
            "title": "Jamie Miller - Here's Your Perfect (Lyrics)",
            "secondDuration": 159,
            "group": "group_4"
        },
        {
            "videoId": "V_m8iMZup4I",
            "title": "twenty one pilots - Christmas Saves The Year (Lyrics)",
            "secondDuration": 213,
            "group": "group_4"
        },
        {
            "videoId": "-D8OcnyeLdI",
            "title": "Natalie Taylor - Surrender (Lyrics)",
            "secondDuration": 185,
            "group": "group_4"
        },
        {
            "videoId": "xGSaPto0ZXY",
            "title": "Troye Sivan - 10/10 (Lyrics)",
            "secondDuration": 189,
            "group": "group_4"
        },
        {
            "videoId": "n8_H2sciTj4",
            "title": "salem ilese - mad at 2020 (Lyrics)",
            "secondDuration": 182,
            "group": "group_4"
        },
        {
            "videoId": "BT_19i4ZpdY",
            "title": "JVKE - Upside Down (Lyrics) \"Up down right down looking for your love right now\" [TikTok Song]",
            "secondDuration": 119,
            "group": "group_4"
        },
        {
            "videoId": "91fmlnMKT1A",
            "title": "ZAYN - When Love's Around (Lyrics) Ft. Syd",
            "secondDuration": 193,
            "group": "group_4"
        },
        {
            "videoId": "eSrXfqhJm4o",
            "title": "SLANDER - Love is Gone (Lyrics) Ft. Dylan Matthew",
            "secondDuration": 176,
            "group": "group_4"
        },
        {
            "videoId": "CqKZM9JMJls",
            "title": "Imagine Dragons - Wrecked (Lyrics)",
            "secondDuration": 244,
            "group": "group_4"
        },
        {
            "videoId": "3Plgp1YtVRQ",
            "title": "Quinn XCII - We Don't Talk Enough (Lyrics) Ft. Alexander 23",
            "secondDuration": 149,
            "group": "group_4"
        },
        {
            "videoId": "6rwYqSW9Owc",
            "title": "Justin Bieber - Unstable (Lyrics) ft. The Kid LAROI",
            "secondDuration": 199,
            "group": "group_4"
        },
        {
            "videoId": "z_zGAV0iMac",
            "title": "Sean Paul - No Lie (Lyrics) ft. Dua Lipa",
            "secondDuration": 223,
            "group": "group_4"
        },
        {
            "videoId": "KZup-NdZxRE",
            "title": "Ed Sheeran - Bad Habits (Lyrics)",
            "secondDuration": 236,
            "group": "group_4"
        },
        {
            "videoId": "9C9EAIh3OiQ",
            "title": "Powfu - death bed (coffee for your head) (Lyrics) ft. beabadoobee",
            "secondDuration": 175,
            "group": "group_4"
        },
        {
            "videoId": "U_vl_Ccsn0U",
            "title": "Duncan Laurence - Arcade (Lyrics)",
            "secondDuration": 184,
            "group": "group_4"
        },
        {
            "videoId": "8P4-bOmL27M",
            "title": "Dua Lipa - Levitating (Lyrics) Ft. DaBaby",
            "secondDuration": 204,
            "group": "group_4"
        },
        {
            "videoId": "PxggecKmwqs",
            "title": "Twenty One Pilots - Saturday (Lyrics)",
            "secondDuration": 213,
            "group": "group_4"
        },
        {
            "videoId": "iFAs-OAr4ds",
            "title": "Sam Fischer - People I Don't Know (Lyrics)",
            "secondDuration": 142,
            "group": "group_4"
        },
        {
            "videoId": "FKvH3ST_ACU",
            "title": "Alex Roma - Let's Not Throw Away A Good Thing (Lyrics)",
            "secondDuration": 184,
            "group": "group_4"
        },
        {
            "videoId": "EI-2oISzXi4",
            "title": "Little Mix - Break Up Song (Acoustic) [Lyrics]",
            "secondDuration": 203,
            "group": "group_4"
        },
        {
            "videoId": "IsjGY3U3w84",
            "title": "Miley Cyrus - Prisoner (Lyrics) ft. Dua Lipa",
            "secondDuration": 168,
            "group": "group_4"
        },
        {
            "videoId": "FmjBw3Bikck",
            "title": "Bebe Rexha - Trust Fall (Lyrics)",
            "secondDuration": 191,
            "group": "group_4"
        },
        {
            "videoId": "tcwFOgohjMg",
            "title": "GAYLE - ​abcdefu (Lyrics)",
            "secondDuration": 169,
            "group": "group_4"
        },
        {
            "videoId": "lpegScplYuM",
            "title": "Alicia Keys - Gramercy Park (Lyrics)",
            "secondDuration": 193,
            "group": "group_4"
        },
        {
            "videoId": "pkx0euCaB8w",
            "title": "Lil Nas X - MONTERO (Call Me By Your Name) (Lyrics)",
            "secondDuration": 138,
            "group": "group_4"
        },
        {
            "videoId": "u3RF16S4XH0",
            "title": "Lennon Stella - Older Than I Am (Lyrics)",
            "secondDuration": 182,
            "group": "group_4"
        },
        {
            "videoId": "eWBSJYR9egk",
            "title": "Sam Fischer, Demi Lovato - What Other People Say (Lyrics)",
            "secondDuration": 228,
            "group": "group_4"
        },
        {
            "videoId": "qMhH_8Rv2wo",
            "title": "Sean Paul - No Lie (Lyrics) ft. Dua Lipa",
            "secondDuration": 223,
            "group": "group_4"
        },
        {
            "videoId": "nN6ZlmUY3Xs",
            "title": "Justin Bieber - Favorite Girl (Lyrics)",
            "secondDuration": 258,
            "group": "group_4"
        },
        {
            "videoId": "z0dUSRcs7xA",
            "title": "Emmy Meli - I Am Woman (Lyrics) \"I Am Woman, I Am Fearless, I Am Sexy, I Am Devine\"",
            "secondDuration": 233,
            "group": "group_4"
        },
        {
            "videoId": "-N0JEDhj978",
            "title": "Sia - Snowman (Lyrics) \"Let's go below zero and hide from the sun\"",
            "secondDuration": 166,
            "group": "group_4"
        },
        {
            "videoId": "4EGIvsqq4xs",
            "title": "Justin Bieber - Somebody (Lyrics)",
            "secondDuration": 220,
            "group": "group_4"
        },
        {
            "videoId": "15au9YhxhiE",
            "title": "One Direction - Olivia (Lyrics) \"I love, I love Olivia\" (Tiktok Song)",
            "secondDuration": 159,
            "group": "group_4"
        },
        {
            "videoId": "8CFLSTOhBkU",
            "title": "Demi Lovato - Met Him Last Night (Lyrics) Ft. Ariana Grande",
            "secondDuration": 241,
            "group": "group_4"
        },
        {
            "videoId": "GEd_9R9g5P8",
            "title": "Jeremy Zucker & Chelsea Cutler - emily (Lyrics)",
            "secondDuration": 267,
            "group": "group_4"
        },
        {
            "videoId": "nhPddhuPmlY",
            "title": "Demi Lovato - Melon Cake (Lyrics)",
            "secondDuration": 253,
            "group": "group_4"
        },
        {
            "videoId": "vVb2hNmbgIY",
            "title": "R3HAB, Astrid S & HRVY - Am I the Only One (Lyrics)",
            "secondDuration": 153,
            "group": "group_4"
        },
        {
            "videoId": "jwaWeyIhBhw",
            "title": "Taylor Swift - Enchanted (Lyrics) \"Please don't be in love With someone else\"",
            "secondDuration": 353,
            "group": "group_4"
        },
        {
            "videoId": "xA5hMFohwxs",
            "title": "Conan Gray - People Watching (Lyrics)",
            "secondDuration": 159,
            "group": "group_4"
        },
        {
            "videoId": "nStPhzlLYi4",
            "title": "Ruel - Hard Sometimes (Lyrics)",
            "secondDuration": 267,
            "group": "group_4"
        },
        {
            "videoId": "vLW1CcbFh18",
            "title": "Olivia Rodrigo - traitor (Lyrics)",
            "secondDuration": 270,
            "group": "group_4"
        },
        {
            "videoId": "Q9EGq2jzcqk",
            "title": "Kiana Lede - Honest. (Lyrics)",
            "secondDuration": 158,
            "group": "group_4"
        },
        {
            "videoId": "ooNMAXYdEpw",
            "title": "Sara Bareilles - Little Voice [Lyrics] (From the Apple TV  Original Series \"Little Voice\")",
            "secondDuration": 146,
            "group": "group_4"
        },
        {
            "videoId": "ZMkqylrtTDo",
            "title": "Pink - We Could Have It All (Lyrics)",
            "secondDuration": 275,
            "group": "group_4"
        },
        {
            "videoId": "mS9LgSEjh8s",
            "title": "Ed Sheeran - Bad Habits (Lyrics)",
            "secondDuration": 236,
            "group": "group_4"
        },
        {
            "videoId": "oHzF7RC1Tik",
            "title": "Aurora - A Different Kind of Human (Lyrics)",
            "secondDuration": 242,
            "group": "group_4"
        }
    ],
    "nbPages": 8,
    "nbResults": 360
}