{
    "currentPage": 1363,
    "pageSize": 10,
    "items": [
        {
            "videoId": "i9AdOBlQlh4",
            "title": "Trump Invokes Defense Production Act To Make 'Important' Coronavirus Supplies | NBC News",
            "secondDuration": 98,
            "group": "group_7"
        },
        {
            "videoId": "R18aEaO5gCk",
            "title": "Morning News NOW Full Broadcast - Oct. 7",
            "secondDuration": 3015,
            "group": "group_7"
        },
        {
            "videoId": "rKPYeRcjKPg",
            "title": "President Obama Jokes To Keep State of The Union Short | NBC News",
            "secondDuration": 55,
            "group": "group_7"
        },
        {
            "videoId": "Y37JGgYGADg",
            "title": "Press Secretary Sarah Huckabee Sanders On President Donald Trump's First Year In Office | NBC News",
            "secondDuration": 367,
            "group": "group_7"
        },
        {
            "videoId": "_9Bma0hLVG8",
            "title": "Are Crickets Food of the Future? | Startups | NBC News",
            "secondDuration": 158,
            "group": "group_7"
        },
        {
            "videoId": "ygbgNMuv03Y",
            "title": "Old Yoga Mat Lying Around? Here Are 3 Clever Ways To Reuse It | Better | NBC News",
            "secondDuration": 73,
            "group": "group_7"
        },
        {
            "videoId": "wZiJOlncJNk",
            "title": "TODAY Fairy Tale",
            "secondDuration": 31,
            "group": "group_7"
        },
        {
            "videoId": "mBsS5NaUgxQ",
            "title": "All Maria Mancia Knows Is That Her Grandson Is In A Place Called Arizona | NBC News",
            "secondDuration": 125,
            "group": "group_7"
        },
        {
            "videoId": "RBFNn9hhTiA",
            "title": "Police Charge Men With Animal Cruelty After Shark Dragging Video | NBC News",
            "secondDuration": 47,
            "group": "group_7"
        },
        {
            "videoId": "CqlO-fep05E",
            "title": "Study Shows AstraZeneca Covid Vaccine May Lower Transmission | NBC Nightly News",
            "secondDuration": 133,
            "group": "group_7"
        }
    ],
    "nbPages": 3683,
    "nbResults": 36826
}