{
    "currentPage": 189,
    "pageSize": 50,
    "items": [
        {
            "videoId": "S1MEI_3lfiY",
            "title": "The SIMATIC ITP1000 - A new level for mobile computing",
            "secondDuration": 120,
            "group": "group_16"
        },
        {
            "videoId": "YBKa4evMYMQ",
            "title": "How Will Energy Solutions Sustain Communities Over The Next Decade?",
            "secondDuration": 164,
            "group": "group_16"
        },
        {
            "videoId": "CkdKaKTlh98",
            "title": "O que são Partidas Híbridas? Economia com ET 200SP Motor Starter",
            "secondDuration": 250,
            "group": "group_16"
        },
        {
            "videoId": "edxqrTxkSXs",
            "title": "Simulation von Antriebssystemen - schnell, einfach und validiert",
            "secondDuration": 425,
            "group": "group_16"
        },
        {
            "videoId": "9MCXKvPmrY8",
            "title": "Smart Polygeneration Microgrid",
            "secondDuration": 159,
            "group": "group_16"
        },
        {
            "videoId": "oD6PEJw0CsE",
            "title": "Industrie 4.0 und die neue Transparenz in der Stromversorgung",
            "secondDuration": 716,
            "group": "group_16"
        },
        {
            "videoId": "Tk6vvA10SNg",
            "title": "Obama und Merkel bei Siemens auf der Hannover Messe 2016",
            "secondDuration": 173,
            "group": "group_16"
        },
        {
            "videoId": "4FYoRcTptHQ",
            "title": "Women Leadership Series, 2021",
            "secondDuration": 66,
            "group": "group_16"
        },
        {
            "videoId": "FlIWGMaIbh0",
            "title": "Protection User Conference | World of Energy Automation | Stephan Flemming",
            "secondDuration": 18,
            "group": "group_16"
        },
        {
            "videoId": "HRSdExM10vw",
            "title": "Desigo CC - How to manage your Electric Vehicle charging system",
            "secondDuration": 102,
            "group": "group_16"
        },
        {
            "videoId": "u_z360mhyjw",
            "title": "Dynamic hydronic balancing: fan coil units",
            "secondDuration": 293,
            "group": "group_16"
        },
        {
            "videoId": "gCuPx9shWT0",
            "title": "Smart buildings - the future of building technology",
            "secondDuration": 447,
            "group": "group_16"
        },
        {
            "videoId": "wwCtNgShy2g",
            "title": "Safety Integrated bei Rosendahl Nextrom",
            "secondDuration": 200,
            "group": "group_16"
        },
        {
            "videoId": "gR5VGAPGchk",
            "title": "Unlock The Potential with Digitalization, Innovation Day India",
            "secondDuration": 2710,
            "group": "group_16"
        },
        {
            "videoId": "UQsPoXdtgEw",
            "title": "Macchi S.p.A. polyolefin-dedicated (POD)",
            "secondDuration": 124,
            "group": "group_16"
        },
        {
            "videoId": "FvA9ELsEHvo",
            "title": "Condition-based maintenance with MindSphere",
            "secondDuration": 377,
            "group": "group_16"
        },
        {
            "videoId": "TDOO_g7TTt4",
            "title": "Wie verdrahtet man LOGO! CIM?",
            "secondDuration": 247,
            "group": "group_16"
        },
        {
            "videoId": "TdAaaAy_-54",
            "title": "Automated execution of engineering tasks",
            "secondDuration": 462,
            "group": "group_16"
        },
        {
            "videoId": "ZNGeUoqSFVc",
            "title": "Access monitoring of a safety area",
            "secondDuration": 144,
            "group": "group_16"
        },
        {
            "videoId": "5NEKlMATMhk",
            "title": "Ammonia And Fertilizer Production I SIEMENS",
            "secondDuration": 147,
            "group": "group_16"
        },
        {
            "videoId": "J48GLb34i1o",
            "title": "SDV-R medium-voltage, outdoor distribution circuit breakers overview",
            "secondDuration": 79,
            "group": "group_16"
        },
        {
            "videoId": "6EpUOlCIkrk",
            "title": "SIMOTIONによるフレキシブルな統合化オートメーションの実現",
            "secondDuration": 142,
            "group": "group_16"
        },
        {
            "videoId": "7TkHxfHq4DQ",
            "title": "BRAUMAT / SISTAR: Working with the graphic recipe system",
            "secondDuration": 490,
            "group": "group_16"
        },
        {
            "videoId": "cCPq8hiLTSU",
            "title": "MindSphere: an app in 20 minutes",
            "secondDuration": 1538,
            "group": "group_16"
        },
        {
            "videoId": "Dw6JtMLBt98",
            "title": "Land Rover BAR & Siemens #BringTheCupHome",
            "secondDuration": 193,
            "group": "group_16"
        },
        {
            "videoId": "498Va5bg2FA",
            "title": "Invitation to your digital journey with MindSphere @SPS17",
            "secondDuration": 63,
            "group": "group_16"
        },
        {
            "videoId": "ykGCw9sbNk4",
            "title": "Thu Duc Water treatment plant in Vietnam - Mixing the old with the new",
            "secondDuration": 348,
            "group": "group_16"
        },
        {
            "videoId": "I5YRxBIj6II",
            "title": "Siemens at SPS IPC Drives 2017 - Digital Enterprise",
            "secondDuration": 73,
            "group": "group_16"
        },
        {
            "videoId": "oU5oHZ-8FCg",
            "title": "SIMATIC RF100C - Einfache Inbetriebnahme und Diagnose",
            "secondDuration": 99,
            "group": "group_16"
        },
        {
            "videoId": "G-TipQqJq30",
            "title": "Siemens Road Solutions - 360-degree Video",
            "secondDuration": 61,
            "group": "group_16"
        },
        {
            "videoId": "OvlFEr-_ea4",
            "title": "18. Siemens Opera Yarışması",
            "secondDuration": 310,
            "group": "group_16"
        },
        {
            "videoId": "0KeOn24zP3c",
            "title": "LOGO! goes cloud: connessione al cloud con LOGO! Web Editor",
            "secondDuration": 144,
            "group": "group_16"
        },
        {
            "videoId": "5gbk3PGsiu0",
            "title": "Pressure independent control valves: Hydronics made easy",
            "secondDuration": 139,
            "group": "group_16"
        },
        {
            "videoId": "k68_ntiESa0",
            "title": "Ansaugrauchmeldung von Siemens - mehr sehen als andere",
            "secondDuration": 162,
            "group": "group_16"
        },
        {
            "videoId": "wd_ssX0QT9M",
            "title": "17 Year old Engineering Student Builds Artificial Foot for Veteran",
            "secondDuration": 48,
            "group": "group_16"
        },
        {
            "videoId": "wFAhdKWxM9c",
            "title": "Siemens_Digital Enterprise",
            "secondDuration": 944,
            "group": "group_16"
        },
        {
            "videoId": "nF54p8-bHgg",
            "title": "SIRIUS ACT at Leitner Ropeways (EN)",
            "secondDuration": 155,
            "group": "group_16"
        },
        {
            "videoId": "rE8f6_DrD4M",
            "title": "SITRANS LCS050",
            "secondDuration": 49,
            "group": "group_16"
        },
        {
            "videoId": "8P9-Jtr02o0",
            "title": "Siemens en Colombia para Colombia",
            "secondDuration": 279,
            "group": "group_16"
        },
        {
            "videoId": "epQjEbz1twk",
            "title": "Protection - with certainty - Reliable protection with minimal effort",
            "secondDuration": 158,
            "group": "group_16"
        },
        {
            "videoId": "UrcHiTwe1JU",
            "title": "#72 BACnet, the master of building protocols",
            "secondDuration": 537,
            "group": "group_16"
        },
        {
            "videoId": "eM9DncmO-28",
            "title": "Episódio 9 - Os desafios e oportunidades do saneamento no Brasil",
            "secondDuration": 1322,
            "group": "group_16"
        },
        {
            "videoId": "HUkxqxvQmdA",
            "title": "Notre engagement envers le Canada",
            "secondDuration": 161,
            "group": "group_16"
        },
        {
            "videoId": "682mLFWEHzI",
            "title": "Digiplay - The digital playroom",
            "secondDuration": 47,
            "group": "group_16"
        },
        {
            "videoId": "3peMdwXtCzY",
            "title": "PSS®E Advanced Contingency Analysis and RAS Module Demonstration Video",
            "secondDuration": 280,
            "group": "group_16"
        },
        {
            "videoId": "x6iTzKaEOnk",
            "title": "MindSphere - Siemens Cloud for Industry",
            "secondDuration": 108,
            "group": "group_16"
        },
        {
            "videoId": "jO62269EKrg",
            "title": "Siemens Ausbildung // MINTfluencer // Der Cal-COOlator",
            "secondDuration": 82,
            "group": "group_16"
        },
        {
            "videoId": "IMnBVlT0Vv8",
            "title": "Our dual energy challenge: electricity for all and a renewable future",
            "secondDuration": 114,
            "group": "group_16"
        },
        {
            "videoId": "Ksmx9Uv62PU",
            "title": "Die GALVA Anlagen-Technik GmbH setzt auf WinCC Unified",
            "secondDuration": 53,
            "group": "group_16"
        },
        {
            "videoId": "R9p-q8kyecI",
            "title": "Elektrische Schutzkonzepte bei Schiffen und Marinas – Teil1/3 - Normen",
            "secondDuration": 298,
            "group": "group_16"
        }
    ],
    "nbPages": 217,
    "nbResults": 10848
}