{
    "currentPage": 1987,
    "pageSize": 20,
    "items": [
        {
            "videoId": "ZnkvP3oayb0",
            "title": "Ron Paul a 'Real Threat' to Win Iowa Caucus: James Carville on 'GMA'",
            "secondDuration": 250,
            "group": "group_7"
        },
        {
            "videoId": "jKa5mp8TCP0",
            "title": "James Comey - An ABC News Exclusive Event Airs Sunday Night 10/9c on ABC",
            "secondDuration": 31,
            "group": "group_7"
        },
        {
            "videoId": "9G5-Ba8qabc",
            "title": "Build Back Better is a 'bad, bad, bad bill': Cassidy | ABC News",
            "secondDuration": 284,
            "group": "group_7"
        },
        {
            "videoId": "-X81DukC8kU",
            "title": "Craig Sager Dies at 65: Remembering the Legendary Reporter",
            "secondDuration": 24,
            "group": "group_7"
        },
        {
            "videoId": "boYGul_BL90",
            "title": "Breaking down Trump's 1st State of the Union",
            "secondDuration": 712,
            "group": "group_7"
        },
        {
            "videoId": "_mSx_RjJtgU",
            "title": "Could Michele Bachmann Be The Republican Nominee?",
            "secondDuration": 255,
            "group": "group_7"
        },
        {
            "videoId": "QnwRlCl2WUQ",
            "title": "Mueller inquired about Comey and Flynn firings: Sources",
            "secondDuration": 150,
            "group": "group_7"
        },
        {
            "videoId": "kYaGUb6cJl8",
            "title": "Baby George: First Look at Future King of England",
            "secondDuration": 390,
            "group": "group_7"
        },
        {
            "videoId": "eVD3aEXAkO8",
            "title": "Senator Kerry and Lugar on START",
            "secondDuration": 663,
            "group": "group_7"
        },
        {
            "videoId": "HJvR-n13Mls",
            "title": "ABC News Live Update: Wildfires claim lives and raze thousands of homes in the West",
            "secondDuration": 616,
            "group": "group_7"
        },
        {
            "videoId": "cJZwt2tNHq4",
            "title": "Rick Perry on Family Values",
            "secondDuration": 85,
            "group": "group_7"
        },
        {
            "videoId": "lafvyo4VLJs",
            "title": "Lindsay Lohan Steals Necklace? Faces Judge 2/10/2011",
            "secondDuration": 120,
            "group": "group_7"
        },
        {
            "videoId": "qiQfGBOoMPM",
            "title": "Doctors Use Stem Cells to Grow New Windpipes",
            "secondDuration": 126,
            "group": "group_7"
        },
        {
            "videoId": "U9mrMKSPick",
            "title": "Joe Biden: Obama's Plan 'Is Going to Work'",
            "secondDuration": 187,
            "group": "group_7"
        },
        {
            "videoId": "mkF8VLlHSfQ",
            "title": "Katie Holmes Files for Divorce From Tom Cruise",
            "secondDuration": 108,
            "group": "group_7"
        },
        {
            "videoId": "3IK9HBbTUoQ",
            "title": "Golden Globes Fashion: Carson Kressley's Winners and Losers on Red-Carpet",
            "secondDuration": 271,
            "group": "group_7"
        },
        {
            "videoId": "_pt83iLfHto",
            "title": "Johnson & Johnson plans to deliver 20 million vaccines by end of March",
            "secondDuration": 309,
            "group": "group_7"
        },
        {
            "videoId": "BY7tDegMzlY",
            "title": "Best in TV: Best Comedy",
            "secondDuration": 572,
            "group": "group_7"
        },
        {
            "videoId": "3w48LzX9K4k",
            "title": "Aurora, Colorado Shootings: Matthew McConaughey, 'Killer Joe,' 'Magic Mike' Star, On Film Violence",
            "secondDuration": 182,
            "group": "group_7"
        },
        {
            "videoId": "8yhX1NNSnh4",
            "title": "Osama Bin Laden Dead: Inside the Top Secret Operation",
            "secondDuration": 164,
            "group": "group_7"
        }
    ],
    "nbPages": 3352,
    "nbResults": 67037
}