{
    "currentPage": 947,
    "pageSize": 5,
    "items": [
        {
            "videoId": "8QYykyEwdIk",
            "title": "Ep. 1435: Where we reach the big reveal with ScreenRant's Kofi Outlaw",
            "secondDuration": 3028,
            "group": "group_8"
        },
        {
            "videoId": "Ux73egLryIg",
            "title": "Car Tech - Volvo Concept C coupe",
            "secondDuration": 103,
            "group": "group_8"
        },
        {
            "videoId": "39TUe3NiPao",
            "title": "9.7 inch iPad Pro: first hands-on look",
            "secondDuration": 52,
            "group": "group_8"
        },
        {
            "videoId": "Td3lNl5A0LE",
            "title": "The powerful, blazingly-fast LG G2",
            "secondDuration": 162,
            "group": "group_8"
        },
        {
            "videoId": "kCPJ-Nr_hKw",
            "title": "5 Google Maps tips and tricks",
            "secondDuration": 164,
            "group": "group_8"
        }
    ],
    "nbPages": 4124,
    "nbResults": 20619
}