{
    "currentPage": 5380,
    "pageSize": 10,
    "items": [
        {
            "videoId": "97QP2gATg3g",
            "title": "Wounded warriors team up with marine scientists",
            "secondDuration": 107,
            "group": "group_7"
        },
        {
            "videoId": "VEDImszJUvk",
            "title": "David Webb: Immigration should not be about diversity",
            "secondDuration": 233,
            "group": "group_7"
        },
        {
            "videoId": "uNw_XwdzG7M",
            "title": "GOP 2016 candidates storm South Carolina",
            "secondDuration": 212,
            "group": "group_7"
        },
        {
            "videoId": "hVO1rFiSLwU",
            "title": "Leftist group preps for war against Trump-inspired fascists",
            "secondDuration": 384,
            "group": "group_7"
        },
        {
            "videoId": "NhCBqXeTcBo",
            "title": "Johnson & Johnson vaccine is 'safe and effective': FDA",
            "secondDuration": 122,
            "group": "group_7"
        },
        {
            "videoId": "zAtbvOfD9FU",
            "title": "Democrats try to blame Republicans for defunding the police",
            "secondDuration": 371,
            "group": "group_7"
        },
        {
            "videoId": "u_Zt7Ky3nb8",
            "title": "Rep. Issa: Clinton email claims can only go to the voters",
            "secondDuration": 53,
            "group": "group_7"
        },
        {
            "videoId": "a-c-fLbVBKU",
            "title": "'Outnumbered' reacts to Harris' dipping poll numbers: 'She's not up to the task'",
            "secondDuration": 440,
            "group": "group_7"
        },
        {
            "videoId": "ngTNnb1l8vg",
            "title": "Kavanaugh delivered 'haymakers' to pro-choice side: Turley",
            "secondDuration": 459,
            "group": "group_7"
        },
        {
            "videoId": "4QakY1RqkVI",
            "title": "Human life and the left in America",
            "secondDuration": 277,
            "group": "group_7"
        }
    ],
    "nbPages": 7964,
    "nbResults": 79635
}