{
    "currentPage": 38,
    "pageSize": 50,
    "items": [
        {
            "videoId": "tlcgRqkwtV0",
            "title": "January 2 | Chelsea set to sign Demba Ba",
            "secondDuration": 61,
            "group": "group_7"
        },
        {
            "videoId": "h0T03TU0VMs",
            "title": "Liverpool v Wolves: Dalglish hails returning Gerrard",
            "secondDuration": 51,
            "group": "group_7"
        },
        {
            "videoId": "_npzU-xsvD8",
            "title": "Has Mauricio Pochettino Confirmed Tottenham Exit?! | W&L",
            "secondDuration": 1335,
            "group": "group_7"
        },
        {
            "videoId": "jC7wukUBqMI",
            "title": "Footballers Before They Were Famous! | Vol. 3",
            "secondDuration": 103,
            "group": "group_7"
        },
        {
            "videoId": "LeFHbUGaFOY",
            "title": "Jose Mourinho is Michael Essien's Daddy",
            "secondDuration": 64,
            "group": "group_7"
        },
        {
            "videoId": "2nDfod42uh0",
            "title": "Manchester United To Spend £90m On Their Defence This Summer?! | Transfer Talk",
            "secondDuration": 542,
            "group": "group_7"
        },
        {
            "videoId": "uQaYD2e6PIQ",
            "title": "Has Eden Hazard Hinted He Wants To LEAVE Chelsea For Real Madrid?! | Transfer Talk",
            "secondDuration": 374,
            "group": "group_7"
        },
        {
            "videoId": "oLsqV-1mWJM",
            "title": "Chelsea To Make Declan Rice The NEXT £100m Player?! | #TransferTalk",
            "secondDuration": 485,
            "group": "group_7"
        },
        {
            "videoId": "vfHvZDxkZAM",
            "title": "Dimitri Payet | Everything You Need To Know",
            "secondDuration": 300,
            "group": "group_7"
        },
        {
            "videoId": "4Tt9arvjeWY",
            "title": "The Most Underrated Champions League Team Is… | #SundayVibes",
            "secondDuration": 2191,
            "group": "group_7"
        },
        {
            "videoId": "ELkgqduIG1A",
            "title": "OFFICIAL: Manchester United Sign £50M Bruno Fernandes! | Transfer Talk",
            "secondDuration": 558,
            "group": "group_7"
        },
        {
            "videoId": "C5R2Y6bDz0s",
            "title": "France 1-0 Peru | France Are The Most OVERRATED Team At The World Cup Because ... | #FDReacts",
            "secondDuration": 145,
            "group": "group_7"
        },
        {
            "videoId": "6JlhACz2e_w",
            "title": "Careers RUINED By Injury XI",
            "secondDuration": 782,
            "group": "group_7"
        },
        {
            "videoId": "-Makju1v8RQ",
            "title": "10 Most UNFORGIVABLE Football Moments!",
            "secondDuration": 570,
            "group": "group_7"
        },
        {
            "videoId": "rhjddI1p94M",
            "title": "Transfer Talk | Xabi Alonso to Chelsea?",
            "secondDuration": 106,
            "group": "group_7"
        },
        {
            "videoId": "xDSqbxepN4s",
            "title": "Can Liverpool Win The Treble This Season?! | W&L",
            "secondDuration": 1194,
            "group": "group_7"
        },
        {
            "videoId": "TVudeFrWfUU",
            "title": "Manchester City Want To Sign Lionel Messi After He Confirmed Barcelona Exit?! | W&L",
            "secondDuration": 1137,
            "group": "group_7"
        },
        {
            "videoId": "P-oa4P7yHrM",
            "title": "Tottenham 2-4 Barcelona | #ArmchairFans",
            "secondDuration": 8953,
            "group": "group_7"
        },
        {
            "videoId": "eqIY6pTXvYA",
            "title": "June 27 | Portugal v Spain Euro 2012 Semi-Final Preview",
            "secondDuration": 60,
            "group": "group_7"
        },
        {
            "videoId": "Z7D1pOA00iQ",
            "title": "10 Managers Who Did The Impossible",
            "secondDuration": 649,
            "group": "group_7"
        },
        {
            "videoId": "UFBds8PCf5Q",
            "title": "REACTING TO GQ'S PREMIER LEAGUE WINNING TEAMS RANKED BEST TO WORST! | #WNTT",
            "secondDuration": 1156,
            "group": "group_7"
        },
        {
            "videoId": "hvOp_RMlAX8",
            "title": "Joe Gomez Out For SEASON | Liverpool Injury Crisis Explained! | #WNTT",
            "secondDuration": 870,
            "group": "group_7"
        },
        {
            "videoId": "nvi2a0Y9Xgs",
            "title": "Underrated Players YOUR CLUB Should Sign This Summer! | #SundayVibes",
            "secondDuration": 3145,
            "group": "group_7"
        },
        {
            "videoId": "u6exesogTGs",
            "title": "Messi vs Neymar",
            "secondDuration": 91,
            "group": "group_7"
        },
        {
            "videoId": "zmqU_e1PVJM",
            "title": "Real Madrid 3 - 1 PSG | Cristiano Ronaldo Brace Sinks Les Parisiens | Internet Reacts",
            "secondDuration": 75,
            "group": "group_7"
        },
        {
            "videoId": "N54mCRASxuo",
            "title": "Arsene Wenger's reaction to Arsenal's 2-1 defeat to QPR",
            "secondDuration": 82,
            "group": "group_7"
        },
        {
            "videoId": "CFF06xzf1fA",
            "title": "MK Dons 4-0 Man Utd | Top 10 Memes and Tweets!",
            "secondDuration": 61,
            "group": "group_7"
        },
        {
            "videoId": "oE_w5vcpMNI",
            "title": "Will Alexis Sanchez QUIT Arsenal For PSG or Juventus?! | Transfer Talk",
            "secondDuration": 327,
            "group": "group_7"
        },
        {
            "videoId": "azNSFnSoJuo",
            "title": "Paul Pogba AGREES Personal Terms With PSG?! | Transfer Talk",
            "secondDuration": 519,
            "group": "group_7"
        },
        {
            "videoId": "azWW-jw_gNE",
            "title": "Fabrice Muamba \"critically ill\" but stable - March 19",
            "secondDuration": 60,
            "group": "group_7"
        },
        {
            "videoId": "5SM726bUJGU",
            "title": "10 Players Who Left Their Club Too Soon!",
            "secondDuration": 628,
            "group": "group_7"
        },
        {
            "videoId": "OvSmDeToHWo",
            "title": "Paul Pogba to Real Madrid for €133m? | Transfer Talk",
            "secondDuration": 201,
            "group": "group_7"
        },
        {
            "videoId": "OjnOWsccPwE",
            "title": "Transfer Talk | Thiago Alcântara to Man Utd?",
            "secondDuration": 64,
            "group": "group_7"
        },
        {
            "videoId": "HUVTJDSmVGc",
            "title": "Was it a bad idea to expand Euro 2016? | #FDW",
            "secondDuration": 1254,
            "group": "group_7"
        },
        {
            "videoId": "J7zdWeY9JTw",
            "title": "Is The Premier League The Most OVERRATED In Europe?! | #SundayVibes",
            "secondDuration": 2354,
            "group": "group_7"
        },
        {
            "videoId": "sNODcAR0Nrw",
            "title": "10 Players Who Deserved More Respect!",
            "secondDuration": 843,
            "group": "group_7"
        },
        {
            "videoId": "Zki1JUCJQYI",
            "title": "Griezmann, Payet & Lukaku Are Too Good For Their Club Because... | #SundayVibes",
            "secondDuration": 907,
            "group": "group_7"
        },
        {
            "videoId": "zew8vor8UCc",
            "title": "Shinji Kagawa's first interview for Man United",
            "secondDuration": 58,
            "group": "group_7"
        },
        {
            "videoId": "sZmt54AP3RQ",
            "title": "10 Teams To WATCH This Season!",
            "secondDuration": 758,
            "group": "group_7"
        },
        {
            "videoId": "NpTHMouKpQw",
            "title": "10 Stars Destined To LEAVE Their Club!",
            "secondDuration": 643,
            "group": "group_7"
        },
        {
            "videoId": "3O9fv3Nu7Dg",
            "title": "Henrikh Mkhitaryan Is A Better Creator Than Kevin De Bruyne Because... | #The12thMan",
            "secondDuration": 1768,
            "group": "group_7"
        },
        {
            "videoId": "rEeW44ZS830",
            "title": "Transfer Talk | Falcao to Chelsea for £60m?",
            "secondDuration": 77,
            "group": "group_7"
        },
        {
            "videoId": "8Ppr1Sjhwwk",
            "title": "WE HAVE A BIG ANNOUNCEMENT!!!",
            "secondDuration": 41,
            "group": "group_7"
        },
        {
            "videoId": "hMKhygLqQPA",
            "title": "Players Manchester United Missed Out On XI",
            "secondDuration": 647,
            "group": "group_7"
        },
        {
            "videoId": "qN7Lpol3-og",
            "title": "The Player Who Could IMPROVE Manchester United Next Season Is… | #SundayVibes",
            "secondDuration": 2754,
            "group": "group_7"
        },
        {
            "videoId": "QE3xFcfpA5U",
            "title": "Most HORRIFIC Injuries XI Part 2 | Coleman, Ederson, Batty",
            "secondDuration": 642,
            "group": "group_7"
        },
        {
            "videoId": "fSqLjZULIkA",
            "title": "Sepp Blatter racism remarks condemned  |  Lucas to Man United? - Nov 17",
            "secondDuration": 67,
            "group": "group_7"
        },
        {
            "videoId": "dlGdoKRBvE8",
            "title": "“Raheem Sterling Is BETTER Than Eden Hazard” | #HotTakes",
            "secondDuration": 535,
            "group": "group_7"
        },
        {
            "videoId": "946vn61OoiM",
            "title": "Transfer Talk | Vidal to Barcelona? Dzeko to Inter?",
            "secondDuration": 97,
            "group": "group_7"
        },
        {
            "videoId": "BNGjcyOPovU",
            "title": "The Biggest BARGAIN Of The Transfer Window Will Be... | #SundayVibes",
            "secondDuration": 1423,
            "group": "group_7"
        }
    ],
    "nbPages": 77,
    "nbResults": 3837
}