{
    "currentPage": 6,
    "pageSize": 10,
    "items": [
        {
            "videoId": "OA7U99atypQ",
            "title": "Here's why cold atoms are being launched into space",
            "secondDuration": 266,
            "group": "group_6"
        },
        {
            "videoId": "LtY6w1bi1So",
            "title": "2019 Breakthrough of the Year",
            "secondDuration": 329,
            "group": "group_6"
        },
        {
            "videoId": "t3_ckDsM8ds",
            "title": "What makes a happy song? Chances are it has more seventh chords",
            "secondDuration": 128,
            "group": "group_6"
        },
        {
            "videoId": "JQlxGDNc2c8",
            "title": "Snippet: Watch the world’s loudest bird scream for a mate",
            "secondDuration": 27,
            "group": "group_6"
        },
        {
            "videoId": "KuYqgrhirqc",
            "title": "Ancient earthquake and flood may have led to China's earliest empire",
            "secondDuration": 153,
            "group": "group_6"
        },
        {
            "videoId": "TYGITwVG71A",
            "title": "Watch water droplets literally jump off a ‘water-hating’ material",
            "secondDuration": 82,
            "group": "group_6"
        },
        {
            "videoId": "VDcSmI0C8fE",
            "title": "Can you tell how this frog is feeling just from his voice?",
            "secondDuration": 84,
            "group": "group_6"
        },
        {
            "videoId": "QFqyCKNhE6U",
            "title": "Podcast (audio only): Peering inside giant planets, and fighting Ebola in the face of fake news",
            "secondDuration": 1419,
            "group": "group_6"
        },
        {
            "videoId": "PsQSEp-01tQ",
            "title": "First footage of True's beaked whales underwater",
            "secondDuration": 46,
            "group": "group_6"
        },
        {
            "videoId": "JZUO3l4U-aY",
            "title": "How sponges ‘spike’ themselves with glass",
            "secondDuration": 137,
            "group": "group_6"
        }
    ],
    "nbPages": 75,
    "nbResults": 748
}