{
    "currentPage": 3611,
    "pageSize": 20,
    "items": [
        {
            "videoId": "zWcQqPxPjuE",
            "title": "Starting a restaurant during a pandemic",
            "secondDuration": 140,
            "group": "group_7"
        },
        {
            "videoId": "bDeVX4N0Iuk",
            "title": "Stacey Abrams acknowledges she won't win Georgia governor's race",
            "secondDuration": 498,
            "group": "group_7"
        },
        {
            "videoId": "SjFokiN8FCg",
            "title": "Biden and Harris gearing up to travel nationwide to promote American Rescue Plan",
            "secondDuration": 482,
            "group": "group_7"
        },
        {
            "videoId": "1tRwYRpqfXk",
            "title": "Leslie Stahl on 'Big Teddy'",
            "secondDuration": 227,
            "group": "group_7"
        },
        {
            "videoId": "5uqs0YfN-DE",
            "title": "President Trump swears in new HHS Secretary Alex Azar",
            "secondDuration": 649,
            "group": "group_7"
        },
        {
            "videoId": "UZWD0u1pBfQ",
            "title": "Pompeo urges Middle Eastern countires to unite against Iran",
            "secondDuration": 404,
            "group": "group_7"
        },
        {
            "videoId": "XEyK5giCV-8",
            "title": "This week in Washington: Health care delayed, travel ban implemented",
            "secondDuration": 351,
            "group": "group_7"
        },
        {
            "videoId": "8kx9N_YELKY",
            "title": "Congress works to avert government shutdown with stopgap funding bill",
            "secondDuration": 837,
            "group": "group_7"
        },
        {
            "videoId": "Ydff0y1k_4U",
            "title": "Rohingya refugees pour into Bangladesh after fleeing violence in Myanmar",
            "secondDuration": 363,
            "group": "group_7"
        },
        {
            "videoId": "Ex4L0NFYvYI",
            "title": "Giffords aide: She was thrilled about House return",
            "secondDuration": 146,
            "group": "group_7"
        },
        {
            "videoId": "-jS0ic5riBM",
            "title": "Biden discusses supply chain issues | full video",
            "secondDuration": 1075,
            "group": "group_7"
        },
        {
            "videoId": "Wy9MVDRNfJY",
            "title": "Scott Pelley on DNC email leak and Clinton, Kaine interview",
            "secondDuration": 381,
            "group": "group_7"
        },
        {
            "videoId": "slveYhmQfrY",
            "title": "New H1N1 Concerns",
            "secondDuration": 111,
            "group": "group_7"
        },
        {
            "videoId": "SZDwCbUmXyc",
            "title": "Steve Bannon to surrender over contempt of Congress charges",
            "secondDuration": 385,
            "group": "group_7"
        },
        {
            "videoId": "CdajmlmeTRY",
            "title": "Former Afghan journalist's murder sparks outrage from women's rights activists",
            "secondDuration": 416,
            "group": "group_7"
        },
        {
            "videoId": "x5g2b2gp28E",
            "title": "U.S. backing France in Mali anti-terror effort",
            "secondDuration": 116,
            "group": "group_7"
        },
        {
            "videoId": "Hnlvj4EV1wE",
            "title": "Barefoot Bandit Arrest Caught on Tape",
            "secondDuration": 64,
            "group": "group_7"
        },
        {
            "videoId": "S-8RGje6LA0",
            "title": "Acting education secretary on student debt problem",
            "secondDuration": 77,
            "group": "group_7"
        },
        {
            "videoId": "gEGMDVemMrM",
            "title": "DHS Secretary Mayorkas defends Biden administration's border policy as migrant numbers rise",
            "secondDuration": 585,
            "group": "group_7"
        },
        {
            "videoId": "hVreTYHukwk",
            "title": "90-year-old man and 85-year-old woman hold Zoom wedding after spring nuptials were canceled due t…",
            "secondDuration": 35,
            "group": "group_7"
        }
    ],
    "nbPages": 4227,
    "nbResults": 84536
}