{
    "currentPage": 252,
    "pageSize": 10,
    "items": [
        {
            "videoId": "M3peXWNZjD0",
            "title": "FBI Seized Michael Cohen's Records Related To The Payment To Stormy Daniels And More | CNBC",
            "secondDuration": 81,
            "group": "group_7"
        },
        {
            "videoId": "2LzHTEyiy9c",
            "title": "How To Think About Personal Finance: Explained By NYT's John Schwartz | CNBC",
            "secondDuration": 418,
            "group": "group_7"
        },
        {
            "videoId": "RJ5EuoQevPc",
            "title": "Week In Review: Facebook CEO Mark Zuckerberg Testifies On Capitol Hill | CNBC",
            "secondDuration": 945,
            "group": "group_7"
        },
        {
            "videoId": "rCEOlPLszvA",
            "title": "Qualcomm CEO Steve Mollenkopf On Legal Battle With Apple And iPhone Royalties | CNBC",
            "secondDuration": 702,
            "group": "group_7"
        },
        {
            "videoId": "lmDitcxGVX4",
            "title": "This Painting Could Fetch More Than $150 Million | CNBC",
            "secondDuration": 64,
            "group": "group_7"
        },
        {
            "videoId": "3I7jIEMZVhg",
            "title": "White House Holds Daily Press Briefing - May 17, 2018 | CNBC",
            "secondDuration": 968,
            "group": "group_7"
        },
        {
            "videoId": "A6L6faJX5DA",
            "title": "Trader Sees One European Market Moving Even Lower | Trading Nation | CNBC",
            "secondDuration": 256,
            "group": "group_7"
        },
        {
            "videoId": "_oOObWe_YXo",
            "title": "How The Defense Industry Profits From Militarizing The Police",
            "secondDuration": 647,
            "group": "group_7"
        },
        {
            "videoId": "1HM4TctxZGI",
            "title": "Why Celebrity CEOs Like Elon Musk Don't Guarantee Profits",
            "secondDuration": 531,
            "group": "group_7"
        },
        {
            "videoId": "4QzJmbo9MGw",
            "title": "DoubleLine Capital CEO Jeffrey Gundlach: There's No Signs Of Recession Right Now | CNBC",
            "secondDuration": 567,
            "group": "group_7"
        }
    ],
    "nbPages": 267,
    "nbResults": 2666
}