{
    "currentPage": 2470,
    "pageSize": 5,
    "items": [
        {
            "videoId": "Q1NYifY_fCg",
            "title": "Georgia Tech vs. Syracuse Women's Basketball Highlights (2019-20)",
            "secondDuration": 93,
            "group": "group_7"
        },
        {
            "videoId": "w6i6qa9taMk",
            "title": "Syracuse's Jerami Grant Throws Down Monster Putback Jam | ACC Must See Moment",
            "secondDuration": 44,
            "group": "group_7"
        },
        {
            "videoId": "fYah9W36cK8",
            "title": "Florida State vs. Wake Forest Football Highlights (2021)",
            "secondDuration": 146,
            "group": "group_7"
        },
        {
            "videoId": "V2BXNaxX4m4",
            "title": "ACC Must See Moment | GT's Quayshawn Nealy Stretches Out for Interception | ACCDigitalNetwork",
            "secondDuration": 46,
            "group": "group_7"
        },
        {
            "videoId": "Hl8RakPBTy0",
            "title": "Louisville vs. Notre Dame Women's Basketball Highlights (2021-22)",
            "secondDuration": 145,
            "group": "group_7"
        }
    ],
    "nbPages": 4883,
    "nbResults": 24413
}