{
    "currentPage": 21,
    "pageSize": 5,
    "items": [
        {
            "videoId": "cncL3aSGh6M",
            "title": "FUNNY BODYBUILDING MOMENTS!! Throwback Thursday Ep. 13",
            "secondDuration": 637,
            "group": "group_15"
        },
        {
            "videoId": "J9MtPTO7kgw",
            "title": "I Bought a Range Rover...",
            "secondDuration": 1187,
            "group": "group_15"
        },
        {
            "videoId": "OYOipvilpT0",
            "title": "IIFYM Full Day of Eating! Ep. 58 - Pizza & McDonald's",
            "secondDuration": 895,
            "group": "group_15"
        },
        {
            "videoId": "_M3CeOtc41M",
            "title": "HUGE FOOD DELIVERY!! Evening of Bulking",
            "secondDuration": 731,
            "group": "group_15"
        },
        {
            "videoId": "IXCRoNgR6mc",
            "title": "REDEMPTION!! Deadlifts - Cycle 6 Week 3",
            "secondDuration": 292,
            "group": "group_15"
        }
    ],
    "nbPages": 258,
    "nbResults": 1290
}