{
    "currentPage": 234,
    "pageSize": 5,
    "items": [
        {
            "videoId": "xZ2Y0B32MQA",
            "title": "Ellie Goulding, blackbear - Worry About Me (Lyrics)",
            "secondDuration": 180,
            "group": "group_4"
        },
        {
            "videoId": "6x_auS9HRQg",
            "title": "Tate McRae - rubberband (Lyrics)",
            "secondDuration": 144,
            "group": "group_4"
        },
        {
            "videoId": "mWVmu17ySuk",
            "title": "Tones and I - Dance Monkey (Lyrics)",
            "secondDuration": 208,
            "group": "group_4"
        },
        {
            "videoId": "9PPZAZeqJ_E",
            "title": "Jeremy Zucker & Chelsea Cutler - This Is How You Fall In Love (Lyrics)",
            "secondDuration": 172,
            "group": "group_4"
        },
        {
            "videoId": "Q1BuVz_3lWc",
            "title": "[Dubstep] Phantom Sage - MIKO",
            "secondDuration": 319,
            "group": "group_4"
        }
    ],
    "nbPages": 360,
    "nbResults": 1800
}