{
    "currentPage": 57,
    "pageSize": 5,
    "items": [
        {
            "videoId": "PfCqSTKhi0A",
            "title": "1 MILLION!",
            "secondDuration": 568,
            "group": "group_3"
        },
        {
            "videoId": "gV4TWLH1GAM",
            "title": "Shabu Shabu in Taipei (富樂台式涮涮鍋)",
            "secondDuration": 412,
            "group": "group_3"
        },
        {
            "videoId": "qGwibq3JTdI",
            "title": "Manila Chinatown (Binondo) Food Guide - BLACK CHICKEN SOUP and Chinese Filipino Food in Philippines!",
            "secondDuration": 1435,
            "group": "group_3"
        },
        {
            "videoId": "VoHX7Hnf40o",
            "title": "Shish Kebabs Meat Platter in Jordan!",
            "secondDuration": 1376,
            "group": "group_3"
        },
        {
            "videoId": "ohsbkNjxZH0",
            "title": "Supersize BURGER!! 🍔 Eating an 11 Pound GIANT BEEF Cheeseburger!!",
            "secondDuration": 1429,
            "group": "group_3"
        }
    ],
    "nbPages": 240,
    "nbResults": 1199
}